pyqlikengine/__init__.py
pyqlikengine/engine.py
pyqlikengine/engine_app_api.py
pyqlikengine/engine_communicator.py
pyqlikengine/engine_field_api.py
pyqlikengine/engine_generic_object_api.py
pyqlikengine/engine_global_api.py
pyqlikengine/engine_helper.py
pyqlikengine/structs.py
pyqlikengine-0.0.2.dist-info/LICENSE
pyqlikengine-0.0.2.dist-info/METADATA
pyqlikengine-0.0.2.dist-info/WHEEL
pyqlikengine-0.0.2.dist-info/top_level.txt
pyqlikengine-0.0.2.dist-info/RECORD
