Metadata-Version: 2.1
Name: pyqlikengine
Version: 0.0.2
Summary: Python wrapper around Qlik Engine JSON API
Home-page: https://github.com/jhettler/pyqlikengine
Author: Jakub Hettler
Author-email: jakub.hettler@gmail.com
License: UNKNOWN
Platform: UNKNOWN
Classifier: Programming Language :: Python :: 3
Classifier: License :: OSI Approved :: MIT License
Classifier: Operating System :: OS Independent
Requires-Python: >=3.6
Requires-Dist: websocket-client (>=0.47.0)
